kornia_rs-0.1.10.dist-info/METADATA
kornia_rs-0.1.10.dist-info/WHEEL
kornia_rs-0.1.10.dist-info/licenses/LICENSE
kornia_rs/__init__.py
kornia_rs/kornia_rs.cpython-314t-x86_64-linux-gnu.so
kornia_rs-0.1.10.dist-info/RECORD
