Metadata-Version: 2.4
Name: kornia_rs
Version: 0.1.10
Classifier: Intended Audience :: Science/Research
Classifier: Operating System :: OS Independent
Classifier: License :: OSI Approved :: Apache Software License
Classifier: Programming Language :: Python
Classifier: Programming Language :: Python :: 3
Classifier: Programming Language :: Python :: 3 :: Only
Classifier: Programming Language :: Python :: 3.8
Classifier: Programming Language :: Python :: 3.9
Classifier: Programming Language :: Python :: 3.10
Classifier: Programming Language :: Python :: 3.11
Classifier: Programming Language :: Python :: 3.12
Classifier: Programming Language :: Python :: 3.13
Classifier: Programming Language :: Python :: 3.14
Classifier: Programming Language :: Python :: Free Threading :: 3 - Stable
Classifier: Programming Language :: Rust
Classifier: Topic :: Scientific/Engineering
Classifier: Programming Language :: Rust
Classifier: Programming Language :: Python :: Implementation :: CPython
Classifier: Programming Language :: Python :: Implementation :: PyPy
License-File: LICENSE
Summary: Low level implementations for computer vision in Rust
Keywords: computer vision,rust
Home-Page: http://kornia.org
Author-email: Edgar Riba <edgar@kornia.org>
Maintainer-email: Edgar Riba <edgar@kornia.org>
Requires-Python: >=3.8
Project-URL: homepage, http://www.kornia.org
Project-URL: documentation, https://kornia.readthedocs.io
Project-URL: repository, https://github.com/kornia/kornia-rs
